{"changelog.md":"B8O1LWiG","developer_api.md":"Cvfyka0X","developer_contributing.md":"DJ-TqVJv","developer_icon-migration.md":"B-jtgdlM","developer_js-php-modernization-plan.md":"Bb3KQ9yP","developer_v3-changes.md":"DVPZBgTg","guide_faq.md":"C0BvW6nh","guide_getting-started.md":"DbT121eA","guide_how-to-learn.md":"DRtwGqxO","guide_how-to-use.md":"Dll6op2m","guide_installation.md":"Cf2KlytL","guide_post-installation.md":"CVkb7DLj","guide_troubleshooting_ipad.md":"DLwINN0X","guide_troubleshooting_wordpress.md":"BNCUbkXq","guide_upgrade.md":"DUAITaJt","index.md":"CfRhdxOD","legal_license.md":"CSn3UMW8","legal_links.md":"DE6l5SW6","legal_third-party-licenses.md":"AM24dijs","reference_database-schema.md":"IbR0ML6E","reference_export-templates.md":"V4de5Gbu","reference_features.md":"C9eg8jGp","reference_keyboard-shortcuts.md":"DnHCnyN9","reference_language-setup.md":"CUkll5hM","reference_new-features.md":"Cd6no244","reference_restrictions.md":"DljYZhD_","reference_term-scores.md":"lnIZ7pv_"}
